simple_interpolator/__init__.py
simple_interpolator/interpolator.py
simple_interpolator/stylizer.py
simple_interpolator-0.1.2.dist-info/METADATA
simple_interpolator-0.1.2.dist-info/WHEEL
simple_interpolator-0.1.2.dist-info/top_level.txt
simple_interpolator-0.1.2.dist-info/RECORD
