Metadata-Version: 2.1
Name: simple-interpolator
Version: 0.1.2
Summary: A simple interpolator.
Author: var-pi (Stefan Ehin)
Author-email: <stefanehin4@gmail.com>
Keywords: python,interpolation,bilinear,math,graph,3D
Classifier: Development Status :: 1 - Planning
Classifier: Intended Audience :: Developers
Classifier: Programming Language :: Python :: 3
Classifier: Operating System :: Unix
Classifier: Operating System :: MacOS :: MacOS X
Classifier: Operating System :: Microsoft :: Windows
Requires-Dist: matplotlib
Requires-Dist: numpy
